prmxctrl/__init__.py
prmxctrl/client.py
prmxctrl/base/__init__.py
prmxctrl/base/endpoint_base.py
prmxctrl/base/exceptions.py
prmxctrl/base/http_client.py
prmxctrl/base/types.py
prmxctrl/endpoints/__init__.py
prmxctrl/endpoints/access/__init__.py
prmxctrl/endpoints/access/acl.py
prmxctrl/endpoints/access/domains.py
prmxctrl/endpoints/access/groups.py
prmxctrl/endpoints/access/openid.py
prmxctrl/endpoints/access/password.py
prmxctrl/endpoints/access/permissions.py
prmxctrl/endpoints/access/roles.py
prmxctrl/endpoints/access/tfa.py
prmxctrl/endpoints/access/ticket.py
prmxctrl/endpoints/access/users.py
prmxctrl/endpoints/access/domains/realm_item/_item.py
prmxctrl/endpoints/access/domains/realm_item/sync/_item.py
prmxctrl/endpoints/access/groups/groupid_item/_item.py
prmxctrl/endpoints/access/openid/auth_url.py
prmxctrl/endpoints/access/openid/login.py
prmxctrl/endpoints/access/roles/roleid_item/_item.py
prmxctrl/endpoints/access/tfa/userid_item/_item.py
prmxctrl/endpoints/access/tfa/userid_item/id_item/_item.py
prmxctrl/endpoints/access/users/userid_item/_item.py
prmxctrl/endpoints/access/users/userid_item/tfa/_item.py
prmxctrl/endpoints/access/users/userid_item/token/_item.py
prmxctrl/endpoints/access/users/userid_item/token/tokenid_item/_item.py
prmxctrl/endpoints/cluster/__init__.py
prmxctrl/endpoints/cluster/acme.py
prmxctrl/endpoints/cluster/backup.py
prmxctrl/endpoints/cluster/backup_info.py
prmxctrl/endpoints/cluster/ceph.py
prmxctrl/endpoints/cluster/config.py
prmxctrl/endpoints/cluster/firewall.py
prmxctrl/endpoints/cluster/ha.py
prmxctrl/endpoints/cluster/jobs.py
prmxctrl/endpoints/cluster/log.py
prmxctrl/endpoints/cluster/metrics.py
prmxctrl/endpoints/cluster/nextid.py
prmxctrl/endpoints/cluster/options.py
prmxctrl/endpoints/cluster/replication.py
prmxctrl/endpoints/cluster/resources.py
prmxctrl/endpoints/cluster/sdn.py
prmxctrl/endpoints/cluster/status.py
prmxctrl/endpoints/cluster/tasks.py
prmxctrl/endpoints/cluster/acme/account.py
prmxctrl-0.1.2.dist-info/licenses/LICENSE
prmxctrl-0.1.2.dist-info/METADATA
prmxctrl-0.1.2.dist-info/WHEEL
prmxctrl-0.1.2.dist-info/top_level.txt
prmxctrl-0.1.2.dist-info/RECORD
