Metadata-Version: 2.4
Name: prmxctrl
Version: 0.1.2
Summary: Type-safe, auto-generated Python SDK for Proxmox VE API v7.4-2
Author-email: Ganzzi <boinguyen9701@gmail.com>
Maintainer-email: Ganzzi <boinguyen9701@gmail.com>
License: MIT
Project-URL: Homepage, https://github.com/Ganzzi/prmxctrl
Project-URL: Documentation, https://prmxctrl.readthedocs.io/
Project-URL: Repository, https://github.com/Ganzzi/prmxctrl
Project-URL: Issues, https://github.com/Ganzzi/prmxctrl/issues
Project-URL: Changelog, https://github.com/Ganzzi/prmxctrl/blob/main/CHANGELOG.md
Keywords: proxmox,api,sdk,async,pydantic,type-safe
Classifier: Development Status :: 3 - Alpha
Classifier: Intended Audience :: Developers
Classifier: License :: OSI Approved :: MIT License
Classifier: Operating System :: OS Independent
Classifier: Programming Language :: Python :: 3
Classifier: Programming Language :: Python :: 3.10
Classifier: Programming Language :: Python :: 3.11
Classifier: Programming Language :: Python :: 3.12
Classifier: Topic :: Software Development :: Libraries :: Python Modules
Classifier: Topic :: System :: Systems Administration
Classifier: Typing :: Typed
Requires-Python: >=3.10
License-File: LICENSE
Requires-Dist: pydantic>=2.0.0
Requires-Dist: httpx>=0.25.0
Requires-Dist: requests>=2.32.5
Requires-Dist: dotenv>=0.9.9
Provides-Extra: dev
Requires-Dist: pytest>=7.4.0; extra == "dev"
Requires-Dist: pytest-asyncio>=0.21.0; extra == "dev"
Requires-Dist: pytest-cov>=4.1.0; extra == "dev"
Requires-Dist: mypy>=1.5.0; extra == "dev"
Requires-Dist: ruff>=0.1.0; extra == "dev"
Requires-Dist: black>=23.9.0; extra == "dev"
Requires-Dist: isort>=5.12.0; extra == "dev"
Requires-Dist: typer>=0.9.0; extra == "dev"
Requires-Dist: jinja2>=3.0.0; extra == "dev"
Dynamic: license-file
